LICENSE.rst
MANIFEST.in
README.rst
pyproject.toml
requirements.txt
setup.py
/home/runner/work/mpi4py-fft/mpi4py-fft/mpi4py_fft/fftw/fftw_planxfftn.c
/home/runner/work/mpi4py-fft/mpi4py-fft/mpi4py_fft/fftw/fftw_xfftn.pyx
/home/runner/work/mpi4py-fft/mpi4py-fft/mpi4py_fft/fftw/utilities.pyx
mpi4py_fft/__init__.py
mpi4py_fft/distarray.py
mpi4py_fft/libfft.py
mpi4py_fft/mpifft.py
mpi4py_fft/pencil.py
mpi4py_fft.egg-info/PKG-INFO
mpi4py_fft.egg-info/SOURCES.txt
mpi4py_fft.egg-info/dependency_links.txt
mpi4py_fft.egg-info/requires.txt
mpi4py_fft.egg-info/top_level.txt
mpi4py_fft/fftw/__init__.py
mpi4py_fft/fftw/factory.py
mpi4py_fft/fftw/fftw_planxfftn.c
mpi4py_fft/fftw/fftw_planxfftn.h
mpi4py_fft/fftw/fftw_xfftn.pxd
mpi4py_fft/fftw/fftw_xfftn.pyx
mpi4py_fft/fftw/utilities.pyx
mpi4py_fft/fftw/xfftn.py
mpi4py_fft/io/__init__.py
mpi4py_fft/io/file_base.py
mpi4py_fft/io/generate_xdmf.py
mpi4py_fft/io/h5py_file.py
mpi4py_fft/io/nc_file.py
tests/test_darray.py
tests/test_fftw.py
tests/test_io.py
tests/test_libfft.py
tests/test_mpifft.py
tests/test_pencil.py
tests/test_speed.py