Metadata-Version: 2.1
Name: mpi4py-fft
Version: 2.0.6
Summary: mpi4py-fft -- Parallel Fast Fourier Transforms (FFTs) using MPI for Python
Home-page: https://github.com/mpi4py/mpi4py-fft
Author: Lisandro Dalcin and Mikael Mortensen
Keywords: Python,FFTW,FFT,DCT,DST,MPI
Classifier: Development Status :: 4 - Beta
Classifier: Environment :: Console
Classifier: Intended Audience :: Developers
Classifier: Intended Audience :: Science/Research
Classifier: Programming Language :: Python
Classifier: Programming Language :: Python :: 2
Classifier: Programming Language :: Python :: 3
Classifier: License :: OSI Approved :: BSD License
Classifier: Topic :: Scientific/Engineering :: Mathematics
Classifier: Topic :: Software Development :: Libraries :: Python Modules
License-File: LICENSE.rst
Requires-Dist: mpi4py
Requires-Dist: numpy
